mujoco/mjx/__init__.py
mujoco/mjx/testspeed.py
mujoco/mjx/viewer.py
mujoco/mjx/_src/__init__.py
mujoco/mjx/_src/collision_convex.py
mujoco/mjx/_src/collision_driver.py
mujoco/mjx/_src/collision_driver_test.py
mujoco/mjx/_src/collision_primitive.py
mujoco/mjx/_src/collision_sdf.py
mujoco/mjx/_src/collision_types.py
mujoco/mjx/_src/constraint.py
mujoco/mjx/_src/constraint_test.py
mujoco/mjx/_src/dataclasses.py
mujoco/mjx/_src/dataclasses_test.py
mujoco/mjx/_src/derivative.py
mujoco/mjx/_src/forward.py
mujoco/mjx/_src/forward_test.py
mujoco/mjx/_src/inverse.py
mujoco/mjx/_src/inverse_test.py
mujoco/mjx/_src/io.py
mujoco/mjx/_src/io_test.py
mujoco/mjx/_src/math.py
mujoco/mjx/_src/math_test.py
mujoco/mjx/_src/mesh.py
mujoco/mjx/_src/mesh_test.py
mujoco/mjx/_src/passive.py
mujoco/mjx/_src/passive_test.py
mujoco/mjx/_src/ray.py
mujoco/mjx/_src/ray_test.py
mujoco/mjx/_src/scan.py
mujoco/mjx/_src/scan_test.py
mujoco/mjx/_src/sensor.py
mujoco/mjx/_src/sensor_test.py
mujoco/mjx/_src/smooth.py
mujoco/mjx/_src/smooth_test.py
mujoco/mjx/_src/solver.py
mujoco/mjx/_src/solver_test.py
mujoco/mjx/_src/support.py
mujoco/mjx/_src/support_test.py
mujoco/mjx/_src/test_util.py
mujoco/mjx/_src/types.py
mujoco/mjx/integration_test/collision_driver_test.py
mujoco/mjx/integration_test/forward_test.py
mujoco/mjx/integration_test/smooth_test.py
mujoco/mjx/test_data/constraints.xml
mujoco/mjx/test_data/convex.xml
mujoco/mjx/test_data/pendula.xml
mujoco/mjx/test_data/quadratic_frictionloss.xml
mujoco/mjx/test_data/ray.xml
mujoco/mjx/test_data/actuator/arm21.xml
mujoco/mjx/test_data/actuator/arm26.xml
mujoco/mjx/test_data/actuator/general_dyntype.xml
mujoco/mjx/test_data/actuator/tendon_force_clamp.xml
mujoco/mjx/test_data/barkour_v0/README.md
mujoco/mjx/test_data/barkour_v0/assets/abduction.stl
mujoco/mjx/test_data/barkour_v0/assets/barkour_v0_mjx.xml
mujoco/mjx/test_data/barkour_v0/assets/body.stl
mujoco/mjx/test_data/barkour_v0/assets/foot.stl
mujoco/mjx/test_data/barkour_v0/assets/handle.stl
mujoco_mjx-3.4.0.dist-info/licenses/LICENSE
mujoco_mjx-3.4.0.dist-info/METADATA
mujoco_mjx-3.4.0.dist-info/WHEEL
mujoco_mjx-3.4.0.dist-info/entry_points.txt
mujoco_mjx-3.4.0.dist-info/top_level.txt
mujoco_mjx-3.4.0.dist-info/RECORD
